setup.py
AdvOptParse.egg-info/PKG-INFO
AdvOptParse.egg-info/SOURCES.txt
AdvOptParse.egg-info/dependency_links.txt
AdvOptParse.egg-info/top_level.txt
advoptparse/__init__.py
advoptparse/console.py
advoptparse/parser.py
advoptparse/state_machine.py
advoptparse/version.py