Metadata-Version: 1.0
Name: AdvOptParse
Version: 0.2.13
Summary: Advanced python commandline argument parser
Home-page: http://github.com/SpaceKookie/AdvOptParse/
Author: Katharina Sabel
Author-email: katharina.sabel@2rsoftworks.de
License: GNU General Public Liense 2.0
Platform: UNKNOWN
